trixelmanagementclient-0.2.0.dist-info/METADATA
trixelmanagementclient-0.2.0.dist-info/WHEEL
trixelmanagementclient-0.2.0.dist-info/entry_points.txt
trixelmanagementclient-0.2.0.dist-info/licenses/LICENSE
trixelmanagementclient/__init__.py
trixelmanagementclient/api/__init__.py
trixelmanagementclient/api/default/__init__.py
trixelmanagementclient/api/default/is_active_active_get.py
trixelmanagementclient/api/default/ping_ping_get.py
trixelmanagementclient/api/default/version_version_get.py
trixelmanagementclient/api/measurement_station/__init__.py
trixelmanagementclient/api/measurement_station/add_measurement_station_measurement_station_put.py
trixelmanagementclient/api/measurement_station/add_sensor_to_measurement_station_measurement_station_sensor_post.py
trixelmanagementclient/api/measurement_station/create_measurement_station_measurement_station_post.py
trixelmanagementclient/api/measurement_station/delete_measurement_station_measurement_station_delete.py
trixelmanagementclient/api/measurement_station/delete_sensor_from_measurement_station_measurement_station_sensor_sensor_id_delete.py
trixelmanagementclient/api/measurement_station/get_measurement_station_count_measurement_stations_get.py
trixelmanagementclient/api/measurement_station/get_measurement_station_detail_measurement_station_get.py
trixelmanagementclient/api/measurement_station/get_sensor_detail_for_measurement_station_measurement_station_sensor_sensor_id_get.py
trixelmanagementclient/api/measurement_station/get_sensors_for_measurement_station_measurement_station_sensors_get.py
trixelmanagementclient/api/trixels/__init__.py
trixelmanagementclient/api/trixels/get_observations_trixel_trixel_id_get.py
trixelmanagementclient/api/trixels/publish_sensor_updates_to_trixels_trixel_update_put.py
trixelmanagementclient/api/trixels/publish_single_sensor_value_trixel_trixel_id_update_sensor_id_put.py
trixelmanagementclient/client.py
trixelmanagementclient/errors.py
trixelmanagementclient/models/__init__.py
trixelmanagementclient/models/http_validation_error.py
trixelmanagementclient/models/measurement.py
trixelmanagementclient/models/measurement_station.py
trixelmanagementclient-0.2.0.dist-info/RECORD
